asciisciit/__init__.py
asciisciit/asciiart.py
asciisciit/asciit.py
asciisciit/conversions.py
asciisciit/lut.py
asciisciit/misc.py
asciisciit/console/__init__.py
asciisciit/console/linux.py
asciisciit/console/windows.py
asciisciit/res/Cousine-Regular.ttf
asciisciit-0.3.0.dist-info/LICENSE
asciisciit-0.3.0.dist-info/METADATA
asciisciit-0.3.0.dist-info/WHEEL
asciisciit-0.3.0.dist-info/entry_points.txt
asciisciit-0.3.0.dist-info/top_level.txt
asciisciit-0.3.0.dist-info/zip-safe
asciisciit-0.3.0.dist-info/RECORD
